README.rst
setup.cfg
setup.py
docs/HISTORY.txt
docs/INSTALL.txt
docs/LICENSE.GPL
docs/LICENSE.txt
transmogrify/__init__.py
transmogrify.filesystem.egg-info/PKG-INFO
transmogrify.filesystem.egg-info/SOURCES.txt
transmogrify.filesystem.egg-info/dependency_links.txt
transmogrify.filesystem.egg-info/entry_points.txt
transmogrify.filesystem.egg-info/namespace_packages.txt
transmogrify.filesystem.egg-info/not-zip-safe
transmogrify.filesystem.egg-info/requires.txt
transmogrify.filesystem.egg-info/top_level.txt
transmogrify/filesystem/__init__.py
transmogrify/filesystem/configure.zcml
transmogrify/filesystem/source.py
transmogrify/filesystem/tests/__init__.py
transmogrify/filesystem/tests/empty.csv
transmogrify/filesystem/tests/nopath.csv
transmogrify/filesystem/tests/test_source.py
transmogrify/filesystem/tests/data/logo.jpg
transmogrify/filesystem/tests/data/noextension
transmogrify/filesystem/tests/data/textfile.txt
transmogrify/filesystem/tests/data/subdir/subsubdir/other.txt
transmogrify/filesystem/tests/metadata/delimiter.csv
transmogrify/filesystem/tests/metadata/file1.txt
transmogrify/filesystem/tests/metadata/metadata.csv
transmogrify/filesystem/tests/metadata/portal_type.csv
transmogrify/filesystem/tests/metadata/subdir/file2.txt
transmogrify/filesystem/tests/metadata/subdir/file3.txt