Metadata-Version: 1.0
Name: transmogrify.filesystem
Version: 1.0b5dev
Summary: Transmogrifier source for reading files from the filesystem
Home-page: http://pypi.python.org/pypi/transmogrify.filesystem
Author: Martin Aspeli
Author-email: optilude@gmail.com
License: GPL
Keywords: plone transmogrifier filesystem
Platform: UNKNOWN
Classifier: Framework :: Plone
Classifier: Programming Language :: Python
Classifier: Topic :: Software Development :: Libraries :: Python Modules
